ansiblebutler/__init__.py
ansiblebutler/__main__.py
ansiblebutler/common/.ansible-butler.yml
ansiblebutler/common/__init__.py
ansiblebutler/common/auth.py
ansiblebutler/common/butler_dumper.py
ansiblebutler/common/dependencies.py
ansiblebutler/common/plugin_map.yml
ansiblebutler/directory/__init__.py
ansiblebutler/directory/_clean.py
ansiblebutler/directory/_initialize.py
ansiblebutler/directory/configs/.ansible-lint
ansiblebutler/directory/templates/playbook.yml.j2
ansiblebutler/directory/templates/.github/ansible-code-bot.yml.j2
ansiblebutler/execution_environment/__init__.py
ansiblebutler/execution_environment/_dependencies.py
ansiblebutler/execution_environment/_initialize.py
ansiblebutler/execution_environment/_inspect.py
ansiblebutler/execution_environment/templates/execution-environment-v3.yml.j2
ansiblebutler/execution_environment/templates/execution-environment.yml.j2
ansiblebutler/external/__init__.py
ansiblebutler/external/introspect.py
ansiblebutler/playbook/__init__.py
ansiblebutler/playbook/_list_collections.py
ansiblebutler/playbook/_update.py
ansiblebutler/role/__init__.py
ansiblebutler/role/_clean.py
ansiblebutler/role/_deps.py
ansiblebutler/role/_list.py
ansiblebutler/role/_mkreadme.py
ansiblebutler/role/templates/README.md.j2
ansiblebutler/role/templates/graph.html.j2
ansiblebutler/template/__init__.py
ansiblebutler/template/_clone.py
ansiblebutler/template/_constants.py
ansible_butler-1.2.5.dist-info/LICENSE
ansible_butler-1.2.5.dist-info/METADATA
ansible_butler-1.2.5.dist-info/WHEEL
ansible_butler-1.2.5.dist-info/entry_points.txt
ansible_butler-1.2.5.dist-info/top_level.txt
ansible_butler-1.2.5.dist-info/RECORD
