Metadata-Version: 2.1
Name: ansible-butler
Version: 1.2.5
Summary: A butler CLI for assistance in managing Ansible projects
Home-page: https://github.com/zjleblanc/ansible-butler
Author: Zach LeBlanc
Author-email: zjleblanc3@gmail.com
Project-URL: Bug Tracker, https://github.com/zjleblanc/ansible-butler/issues
Classifier: Programming Language :: Python :: 3
Classifier: License :: OSI Approved :: GNU General Public License (GPL)
Classifier: Operating System :: OS Independent
Requires-Python: >=3.6
License-File: LICENSE
Requires-Dist: docopt >=0.6.2
Requires-Dist: PyYAML >=5.4.1
Requires-Dist: Jinja2 >=3.0.0
Requires-Dist: mergedeep >=1.3.4
Requires-Dist: ansible >=8.0.0
Requires-Dist: ansible-core >=2.15.0
Requires-Dist: ansible-lint >=6.17.2
Requires-Dist: requirements-parser >=0.5.0
